neuromodels/__init__.py
neuromodels/__version__.py
neuromodels/models/__init__.py
neuromodels/models/hodgkin_huxley.py
neuromodels-0.0.2.dist-info/LICENSE
neuromodels-0.0.2.dist-info/METADATA
neuromodels-0.0.2.dist-info/WHEEL
neuromodels-0.0.2.dist-info/top_level.txt
neuromodels-0.0.2.dist-info/RECORD
